MANIFEST.in
README.rst
onlinenic.py
setup.py
OnlineNIC.egg-info/PKG-INFO
OnlineNIC.egg-info/SOURCES.txt
OnlineNIC.egg-info/dependency_links.txt
OnlineNIC.egg-info/requires.txt
OnlineNIC.egg-info/top_level.txt