Metadata-Version: 1.1
Name: OnlineNIC
Version: 0.1.0
Summary: A simple wrapper for the OnlineNIC API.
Home-page: http://github.com/kolanos/onlinenic
Author: Michael Lavers
Author-email: kolanos@gmail.com
License: MIT
Platform: any
Classifier: Environment :: Web Environment
Classifier: Intended Audience :: Developers
Classifier: License :: OSI Approved :: MIT License
Classifier: Operating System :: OS Independent
Classifier: Programming Language :: Python
Classifier: Topic :: Internet :: WWW/HTTP
Classifier: Topic :: Software Development :: Libraries :: Python Modules
